setup.cfg
setup.py
ldap_mysql_granter/__init__.py
ldap_mysql_granter/__main__.py
ldap_mysql_granter/auto_grant_config.py
ldap_mysql_granter/email_tool.py
ldap_mysql_granter/import_schema_config.py
ldap_mysql_granter/import_schema_tool.py
ldap_mysql_granter/ldap_query_tool.py
ldap_mysql_granter/my_dot_cnf.py
ldap_mysql_granter/mysql_backup_tool.py
ldap_mysql_granter/mysql_grants_generator.py
ldap_mysql_granter/mysql_query_tool.py
ldap_mysql_granter/prod_requirements.txt
ldap_mysql_granter/test_auto_grant_config.py
ldap_mysql_granter/test_email_tool.py
ldap_mysql_granter/test_import_schema_config.py
ldap_mysql_granter/test_import_schema_tool.py
ldap_mysql_granter/test_ldap_query_tool.py
ldap_mysql_granter/test_my_dot_cnf.py
ldap_mysql_granter/test_mysql_backup_tool.py
ldap_mysql_granter/test_mysql_grants_generator.py
ldap_mysql_granter/test_mysql_query_tool.py
ldap_mysql_granter/util.py
ldap_mysql_granter/yaml_config.py
ldap_mysql_granter.egg-info/PKG-INFO
ldap_mysql_granter.egg-info/SOURCES.txt
ldap_mysql_granter.egg-info/dependency_links.txt
ldap_mysql_granter.egg-info/entry_points.txt
ldap_mysql_granter.egg-info/requires.txt
ldap_mysql_granter.egg-info/top_level.txt
ldap_mysql_granter/templates/password_change.py.tmpl
ldap_mysql_granter/templates/password_change_access.tmpl
ldap_mysql_granter/templates/password_change_invite.tmpl