Metadata-Version: 1.0
Name: ldap-mysql-granter
Version: 0.1.0
Summary: ('a configurable ldap group to mysql cluster granter of privileges',)
Home-page: UNKNOWN
Author: Nicholas Flink
Author-email: nicholas@sproutsocial.com
License: UNKNOWN
Platform: UNKNOWN
